{
  "rounds": [
    { "name": "Round of 64" },
    { "name": "Round of 32" },
    { "name": "Sweet Sixteen" },
    { "name": "Elite Eight" },
    { "name": "Final Four" },
    { "name": "Championship" }
  ],
  "teams": {
    "t1": {
      "id": "t1",
      "name": "Auburn",
      "seed": 1,
      "logoUrl": "https://i.turner.ncaa.com/sites/default/files/images/logos/schools/bgl/auburn.svg"
    },
    "t2": {
      "id": "t2",
      "name": "Houston",
      "seed": 1,
      "logoUrl": "https://i.turner.ncaa.com/sites/default/files/images/logos/schools/bgl/houston.svg"
    },
    "t3": {
      "id": "t3",
      "name": "Duke",
      "seed": 1,
      "logoUrl": "https://i.turner.ncaa.com/sites/default/files/images/logos/schools/bgl/duke.svg"
    },
    "t4": {
      "id": "t4",
      "name": "Florida",
      "seed": 1,
      "logoUrl": "https://i.turner.ncaa.com/sites/default/files/images/logos/schools/bgl/florida.svg"
    },
    "t5": {
      "id": "t5",
      "name": "Texas Tech",
      "seed": 3,
      "logoUrl": "https://i.turner.ncaa.com/sites/default/files/images/logos/schools/bgl/texas-tech.svg"
    },
    "t6": {
      "id": "t6",
      "name": "Alabama",
      "seed": 2,
      "logoUrl": "https://i.turner.ncaa.com/sites/default/files/images/logos/schools/bgl/alabama.svg"
    },
    "t7": {
      "id": "t7",
      "name": "Tennessee",
      "seed": 2,
      "logoUrl": "https://i.turner.ncaa.com/sites/default/files/images/logos/schools/bgl/tennessee.svg"
    },
    "t8": {
      "id": "t8",
      "name": "Michigan St.",
      "seed": 2,
      "logoUrl": "https://i.turner.ncaa.com/sites/default/files/images/logos/schools/bgl/michigan-st.svg"
    },
    "t9": {
      "id": "t9",
      "name": "Michigan",
      "seed": 5,
      "logoUrl": "https://i.turner.ncaa.com/sites/default/files/images/logos/schools/bgl/michigan.svg"
    },
    "t10": {
      "id": "t10",
      "name": "Ole Miss",
      "seed": 6,
      "logoUrl": "https://i.turner.ncaa.com/sites/default/files/images/logos/schools/bgl/ole-miss.svg"
    },
    "t11": {
      "id": "t11",
      "name": "Maryland",
      "seed": 4,
      "logoUrl": "https://i.turner.ncaa.com/sites/default/files/images/logos/schools/bgl/maryland.svg"
    },
    "t12": {
      "id": "t12",
      "name": "Arkansas",
      "seed": 10,
      "logoUrl": "https://i.turner.ncaa.com/sites/default/files/images/logos/schools/bgl/arkansas.svg"
    },
    "t13": {
      "id": "t13",
      "name": "Arizona",
      "seed": 4,
      "logoUrl": "https://i.turner.ncaa.com/sites/default/files/images/logos/schools/bgl/arizona.svg"
    },
    "t14": {
      "id": "t14",
      "name": "BYU",
      "seed": 6,
      "logoUrl": "https://i.turner.ncaa.com/sites/default/files/images/logos/schools/bgl/byu.svg"
    },
    "t15": {
      "id": "t15",
      "name": "Purdue",
      "seed": 4,
      "logoUrl": "https://i.turner.ncaa.com/sites/default/files/images/logos/schools/bgl/purdue.svg"
    },
    "t16": {
      "id": "t16",
      "name": "Kentucky",
      "seed": 3,
      "logoUrl": "https://i.turner.ncaa.com/sites/default/files/images/logos/schools/bgl/kentucky.svg"
    },
    "t17": {
      "id": "t17",
      "name": "Clemson",
      "seed": 5,
      "logoUrl": "https://i.turner.ncaa.com/sites/default/files/images/logos/schools/bgl/clemson.svg"
    },
    "t18": {
      "id": "t18",
      "name": "Illinois",
      "seed": 6,
      "logoUrl": "https://i.turner.ncaa.com/sites/default/files/images/logos/schools/bgl/illinois.svg"
    },
    "t19": {
      "id": "t19",
      "name": "UCLA",
      "seed": 7,
      "logoUrl": "https://i.turner.ncaa.com/sites/default/files/images/logos/schools/bgl/ucla.svg"
    },
    "t20": {
      "id": "t20",
      "name": "Gonzaga",
      "seed": 8,
      "logoUrl": "https://i.turner.ncaa.com/sites/default/files/images/logos/schools/bgl/gonzaga.svg"
    },
    "t21": {
      "id": "t21",
      "name": "Georgia",
      "seed": 9,
      "logoUrl": "https://i.turner.ncaa.com/sites/default/files/images/logos/schools/bgl/georgia.svg"
    },
    "t22": {
      "id": "t22",
      "name": "Utah St.",
      "seed": 10,
      "logoUrl": "https://i.turner.ncaa.com/sites/default/files/images/logos/schools/bgl/utah-st.svg"
    },
    "t23": {
      "id": "t23",
      "name": "Xavier",
      "seed": 11,
      "logoUrl": "https://i.turner.ncaa.com/sites/default/files/images/logos/schools/bgl/xavier.svg"
    },
    "t24": {
      "id": "t24",
      "name": "McNeese",
      "seed": 12,
      "logoUrl": "https://i.turner.ncaa.com/sites/default/files/images/logos/schools/bgl/mcneese.svg"
    },
    "t25": {
      "id": "t25",
      "name": "High Point",
      "seed": 13,
      "logoUrl": "https://i.turner.ncaa.com/sites/default/files/images/logos/schools/bgl/high-point.svg"
    },
    "t26": {
      "id": "t26",
      "name": "Troy",
      "seed": 14,
      "logoUrl": "https://i.turner.ncaa.com/sites/default/files/images/logos/schools/bgl/troy.svg"
    },
    "t27": {
      "id": "t27",
      "name": "Wofford",
      "seed": 15,
      "logoUrl": "https://i.turner.ncaa.com/sites/default/files/images/logos/schools/bgl/wofford.svg"
    },
    "t28": {
      "id": "t28",
      "name": "SIU Edwardsville",
      "seed": 16,
      "logoUrl": "https://i.turner.ncaa.com/sites/default/files/images/logos/schools/bgl/siu-edwardsville.svg"
    },
    "t29": {
      "id": "t29",
      "name": "Iowa St",
      "seed": 3,
      "logoUrl": "https://i.turner.ncaa.com/sites/default/files/images/logos/schools/bgl/iowa-st.svg"
    },
    "t30": {
      "id": "t30",
      "name": "Texas A&M",
      "seed": 4,
      "logoUrl": "https://i.turner.ncaa.com/sites/default/files/images/logos/schools/bgl/texas-am.svg"
    },
    "t31": {
      "id": "t31",
      "name": "Marquette",
      "seed": 7,
      "logoUrl": "https://i.turner.ncaa.com/sites/default/files/images/logos/schools/bgl/marquette.svg"
    },
    "t32": {
      "id": "t32",
      "name": "Louisville",
      "seed": 8,
      "logoUrl": "https://i.turner.ncaa.com/sites/default/files/images/logos/schools/bgl/louisville.svg"
    },
    "t33": {
      "id": "t33",
      "name": "Creighton",
      "seed": 9,
      "logoUrl": "https://i.turner.ncaa.com/sites/default/files/images/logos/schools/bgl/creighton.svg"
    },
    "t34": {
      "id": "t34",
      "name": "New Mexico",
      "seed": 10,
      "logoUrl": "https://i.turner.ncaa.com/sites/default/files/images/logos/schools/bgl/new-mexico.svg"
    },
    "t35": {
      "id": "t35",
      "name": "North Carolina",
      "seed": 11,
      "logoUrl": "https://i.turner.ncaa.com/sites/default/files/images/logos/schools/bgl/north-carolina.svg"
    },
    "t36": {
      "id": "t36",
      "name": "UC San Diego",
      "seed": 12,
      "logoUrl": "https://i.turner.ncaa.com/sites/default/files/images/logos/schools/bgl/uc-san-diego.svg"
    },
    "t37": {
      "id": "t37",
      "name": "Yale",
      "seed": 13,
      "logoUrl": "https://i.turner.ncaa.com/sites/default/files/images/logos/schools/bgl/yale.svg"
    },
    "t38": {
      "id": "t38",
      "name": "Lipscomb",
      "seed": 14,
      "logoUrl": "https://i.turner.ncaa.com/sites/default/files/images/logos/schools/bgl/lipscomb.svg"
    },
    "t39": {
      "id": "t39",
      "name": "Bryant",
      "seed": 15,
      "logoUrl": "https://i.turner.ncaa.com/sites/default/files/images/logos/schools/bgl/bryant.svg"
    },
    "t40": {
      "id": "t40",
      "name": "Alabama St.",
      "seed": 15,
      "logoUrl": "https://i.turner.ncaa.com/sites/default/files/images/logos/schools/bgl/alabama-st.svg"
    },
    "t41": {
      "id": "t41",
      "name": "St. Mary's",
      "seed": 7,
      "logoUrl": "https://i.turner.ncaa.com/sites/default/files/images/logos/schools/bgl/st-marys-ca.svg"
    },
    "t42": {
      "id": "t42",
      "name": "Mississippi St.",
      "seed": 8,
      "logoUrl": "https://i.turner.ncaa.com/sites/default/files/images/logos/schools/bgl/mississippi-st.svg"
    },
    "t43": {
      "id": "t43",
      "name": "Baylor",
      "seed": 9,
      "logoUrl": "https://i.turner.ncaa.com/sites/default/files/images/logos/schools/bgl/baylor.svg"
    },
    "t44": {
      "id": "t44",
      "name": "Vanderbilt",
      "seed": 10,
      "logoUrl": "https://i.turner.ncaa.com/sites/default/files/images/logos/schools/bgl/vanderbilt.svg"
    },
    "t45": {
      "id": "t45",
      "name": "VCU",
      "seed": 11,
      "logoUrl": "https://i.turner.ncaa.com/sites/default/files/images/logos/schools/bgl/vcu.svg"
    },
    "t46": {
      "id": "t46",
      "name": "Liberty",
      "seed": 12,
      "logoUrl": "https://i.turner.ncaa.com/sites/default/files/images/logos/schools/bgl/liberty.svg"
    },
    "t47": {
      "id": "t47",
      "name": "Akron",
      "seed": 13,
      "logoUrl": "https://i.turner.ncaa.com/sites/default/files/images/logos/schools/bgl/akron.svg"
    },
    "t48": {
      "id": "t48",
      "name": "Montana",
      "seed": 14,
      "logoUrl": "https://i.turner.ncaa.com/sites/default/files/images/logos/schools/bgl/montana.svg"
    },
    "t49": {
      "id": "t49",
      "name": "Robert Morris",
      "seed": 15,
      "logoUrl": "https://i.turner.ncaa.com/sites/default/files/images/logos/schools/bgl/robert-morris.svg"
    },
    "t50": {
      "id": "t50",
      "name": "Mount St. Mary's",
      "seed": 15,
      "logoUrl": "https://i.turner.ncaa.com/sites/default/files/images/logos/schools/bgl/mt-st-marys.svg"
    },
    "t51": {
      "id": "t51",
      "name": "Memphis",
      "seed": 5,
      "logoUrl": "https://i.turner.ncaa.com/sites/default/files/images/logos/schools/bgl/memphis.svg"
    },
    "t52": {
      "id": "t52",
      "name": "Missouri",
      "seed": 6,
      "logoUrl": "https://i.turner.ncaa.com/sites/default/files/images/logos/schools/bgl/missouri.svg"
    },
    "t53": {
      "id": "t53",
      "name": "Kansas",
      "seed": 7,
      "logoUrl": "https://i.turner.ncaa.com/sites/default/files/images/logos/schools/bgl/kansas.svg"
    },
    "t54": {
      "id": "t54",
      "name": "UConn",
      "seed": 8,
      "logoUrl": "https://i.turner.ncaa.com/sites/default/files/images/logos/schools/bgl/uconn.svg"
    },
    "t55": {
      "id": "t55",
      "name": "Oklahoma",
      "seed": 9,
      "logoUrl": "https://i.turner.ncaa.com/sites/default/files/images/logos/schools/bgl/oklahoma.svg"
    },
    "t56": {
      "id": "t56",
      "name": "Drake",
      "seed": 11,
      "logoUrl": "https://i.turner.ncaa.com/sites/default/files/images/logos/schools/bgl/drake.svg"
    },
    "t57": {
      "id": "t57",
      "name": "Colorado St.",
      "seed": 12,
      "logoUrl": "https://i.turner.ncaa.com/sites/default/files/images/logos/schools/bgl/colorado-st.svg"
    },
    "t58": {
      "id": "t58",
      "name": "Grand Canyon",
      "seed": 13,
      "logoUrl": "https://i.turner.ncaa.com/sites/default/files/images/logos/schools/bgl/grand-canyon.svg"
    },
    "t59": {
      "id": "t59",
      "name": "UNC Wilmington",
      "seed": 14,
      "logoUrl": "https://i.turner.ncaa.com/sites/default/files/images/logos/schools/bgl/unc-wilmington.svg"
    },
    "t60": {
      "id": "t60",
      "name": "Omaha",
      "seed": 15,
      "logoUrl": "https://i.turner.ncaa.com/sites/default/files/images/logos/schools/bgl/neb-omaha.svg"
    },
    "t61": {
      "id": "t61",
      "name": "Norfolk St.",
      "seed": 16,
      "logoUrl": "https://i.turner.ncaa.com/sites/default/files/images/logos/schools/bgl/norfolk-st.svg"
    },
    "t62": {
      "id": "t62",
      "name": "Wisconsin",
      "seed": 3,
      "logoUrl": "https://i.turner.ncaa.com/sites/default/files/images/logos/schools/bgl/wisconsin.svg"
    },
    "t63": {
      "id": "t63",
      "name": "Oregon",
      "seed": 5,
      "logoUrl": "https://i.turner.ncaa.com/sites/default/files/images/logos/schools/bgl/oregon.svg"
    },
    "t64": {
      "id": "t64",
      "name": "St. John's",
      "seed": 2,
      "logoUrl": "https://i.turner.ncaa.com/sites/default/files/images/logos/schools/bgl/st-johns-ny.svg"
    }
  }
}
